LICENSE
MANIFEST.in
README.rst
setup.cfg
setup.py
examples/simple.py
space_track_api/__init__.py
space_track_api/client.py
space_track_api/exc.py
space_track_api/log.py
space_track_api/query.py
space_track_api.egg-info/PKG-INFO
space_track_api.egg-info/SOURCES.txt
space_track_api.egg-info/dependency_links.txt
space_track_api.egg-info/requires.txt
space_track_api.egg-info/top_level.txt