Metadata-Version: 1.1
Name: space-track-api
Version: 1.0.2
Summary: Small helper for `space-track.org` query api.
Home-page: https://github.com/nkoshell/space-track-api
Author: nkoshell
Author-email: nikita.koshelev@gmail.com
License: MIT
Download-URL: https://github.com/nkoshell/space-track-api/archive/1.0.2.tar.gz
Platform: UNKNOWN
